odoo/addons/l10n_ro_config/README.rst
odoo/addons/l10n_ro_config/__init__.py
odoo/addons/l10n_ro_config/__manifest__.py
odoo/addons/l10n_ro_config/init_hook.py
odoo/addons/l10n_ro_config/i18n/bg.po
odoo/addons/l10n_ro_config/i18n/de.po
odoo/addons/l10n_ro_config/i18n/el_GR.po
odoo/addons/l10n_ro_config/i18n/fr.po
odoo/addons/l10n_ro_config/i18n/it.po
odoo/addons/l10n_ro_config/i18n/l10n_ro_config.pot
odoo/addons/l10n_ro_config/i18n/ro.po
odoo/addons/l10n_ro_config/models/__init__.py
odoo/addons/l10n_ro_config/models/account_journal.py
odoo/addons/l10n_ro_config/models/ir_ui_menu.py
odoo/addons/l10n_ro_config/models/l10n_ro_mixin.py
odoo/addons/l10n_ro_config/models/product_template.py
odoo/addons/l10n_ro_config/models/res_bank.py
odoo/addons/l10n_ro_config/models/res_company.py
odoo/addons/l10n_ro_config/models/res_partner.py
odoo/addons/l10n_ro_config/models/template_ro.py
odoo/addons/l10n_ro_config/readme/CONTRIBUTORS.md
odoo/addons/l10n_ro_config/readme/DESCRIPTION.md
odoo/addons/l10n_ro_config/readme/INSTALL.md
odoo/addons/l10n_ro_config/readme/USAGE.md
odoo/addons/l10n_ro_config/security/ro_menus_group.xml
odoo/addons/l10n_ro_config/static/description/icon.png
odoo/addons/l10n_ro_config/static/description/index.html
odoo/addons/l10n_ro_config/tests/__init__.py
odoo/addons/l10n_ro_config/tests/test_bank_account_print_report.py
odoo/addons/l10n_ro_config/tests/test_partner_country_code.py
odoo/addons/l10n_ro_config/views/account_journal.xml
odoo/addons/l10n_ro_config/views/common_report.xml
odoo/addons/l10n_ro_config/views/res_bank_view.xml
odoo/addons/l10n_ro_config/views/res_partner_view.xml
odoo/addons/l10n_ro_config/wizard/__init__.py
odoo/addons/l10n_ro_config/wizard/res_config_settings.py
odoo/addons/l10n_ro_config/wizard/res_config_settings_views.xml
odoo_addon_l10n_ro_config-19.0.0.6.0.1.dist-info/METADATA
odoo_addon_l10n_ro_config-19.0.0.6.0.1.dist-info/WHEEL
odoo_addon_l10n_ro_config-19.0.0.6.0.1.dist-info/top_level.txt
odoo_addon_l10n_ro_config-19.0.0.6.0.1.dist-info/RECORD
